IoTVision/__init__.py
IoTVision/annotator.py
IoTVision/simulator.py
IoTVision-0.2.dist-info/LICENSE
IoTVision-0.2.dist-info/METADATA
IoTVision-0.2.dist-info/WHEEL
IoTVision-0.2.dist-info/top_level.txt
IoTVision-0.2.dist-info/RECORD
